[{"model": "app_product.parametervalue", "pk": 1, "fields": {"value": "6 \u043c\u0435\u0441."}}, {"model": "app_product.parametervalue", "pk": 2, "fields": {"value": "1 \u0433\u043e\u0434"}}, {"model": "app_product.parametervalue", "pk": 3, "fields": {"value": "2 \u0433\u043e\u0434\u0430"}}, {"model": "app_product.parametervalue", "pk": 4, "fields": {"value": "199 \u0433"}}, {"model": "app_product.parametervalue", "pk": 5, "fields": {"value": "355 \u0433"}}, {"model": "app_product.parametervalue", "pk": 6, "fields": {"value": "1 \u043a\u0433"}}, {"model": "app_product.parametervalue", "pk": 7, "fields": {"value": "55 \u043a\u0433"}}, {"model": "app_product.parametervalue", "pk": 8, "fields": {"value": "10.99"}}, {"model": "app_product.parametervalue", "pk": 9, "fields": {"value": "6.3"}}, {"model": "app_product.parametervalue", "pk": 10, "fields": {"value": "5.5"}}, {"model": "app_product.parametervalue", "pk": 11, "fields": {"value": "4000"}}, {"model": "app_product.parametervalue", "pk": 12, "fields": {"value": "10000"}}, {"model": "app_product.parametervalue", "pk": 13, "fields": {"value": "3600"}}]